viewmask/__init__.py
viewmask/cli.py
viewmask/utils.py
viewmask-0.3.1.dist-info/entry_points.txt
viewmask-0.3.1.dist-info/LICENSE
viewmask-0.3.1.dist-info/WHEEL
viewmask-0.3.1.dist-info/METADATA
viewmask-0.3.1.dist-info/RECORD
