Metadata-Version: 2.1
Name: viewmask
Version: 0.3.1
Summary: A Python package and CLI to view XML annotations and NumPy masks.
Home-page: https://github.com/sumanthratna/viewmask
License: MIT
Author: sumanthratna
Author-email: sumanthratna@gmail.com
Requires-Python: >=3.7,<3.10
Classifier: License :: OSI Approved :: MIT License
Classifier: Programming Language :: Python :: 3
Classifier: Programming Language :: Python :: 3.7
Classifier: Programming Language :: Python :: 3.8
Classifier: Programming Language :: Python :: 3.9
Requires-Dist: Pillow (>=8.0.0,<9.0.0)
Requires-Dist: click (>=8.0.1,<9.0.0)
Requires-Dist: dask-image (>=0.6.0,<0.7.0)
Requires-Dist: napari (>=0.4.2,<0.5.0)
Requires-Dist: numpy (>=1.18.4,<2.0.0)
Requires-Dist: opencv-python-headless (>=4.2.0,<5.0.0)
Requires-Dist: openslide-python (>=1.1.1,<2.0.0)
Requires-Dist: scikit-image (>=0.18.1,<0.19.0)
Requires-Dist: scipy (>=1.6.3,<2.0.0)
Project-URL: Documentation, https://viewmask.readthedocs.io/en/latest/
Project-URL: Repository, https://github.com/sumanthratna/viewmask
